sphericaltexture/__init__.py
sphericaltexture/plotting.py
sphericaltexture/spherical_texture.py
sphericaltexture-0.1.1.dist-info/LICENSE
sphericaltexture-0.1.1.dist-info/METADATA
sphericaltexture-0.1.1.dist-info/WHEEL
sphericaltexture-0.1.1.dist-info/RECORD
